PythonOpencvJisuanjiShijueChuyi/README.md
PythonOpencvJisuanjiShijueChuyi/__init__.py
PythonOpencvJisuanjiShijueChuyi/__main__.py
PythonOpencvJisuanjiShijueChuyi/file.epub
PythonOpencvJisuanjiShijueChuyi/index.html
PythonOpencvJisuanjiShijueChuyi/css/__init__.py
PythonOpencvJisuanjiShijueChuyi/css/annotations.css
PythonOpencvJisuanjiShijueChuyi/css/main.css
PythonOpencvJisuanjiShijueChuyi/css/normalize.css
PythonOpencvJisuanjiShijueChuyi/css/popup.css
PythonOpencvJisuanjiShijueChuyi/font/__init__.py
PythonOpencvJisuanjiShijueChuyi/font/fontello.eot
PythonOpencvJisuanjiShijueChuyi/font/fontello.svg
PythonOpencvJisuanjiShijueChuyi/font/fontello.ttf
PythonOpencvJisuanjiShijueChuyi/font/fontello.woff
PythonOpencvJisuanjiShijueChuyi/img/__init__.py
PythonOpencvJisuanjiShijueChuyi/img/annotator-glyph-sprite.png
PythonOpencvJisuanjiShijueChuyi/img/annotator-icon-sprite.png
PythonOpencvJisuanjiShijueChuyi/img/apple-touch-icon.png
PythonOpencvJisuanjiShijueChuyi/img/cancelfullscreen.png
PythonOpencvJisuanjiShijueChuyi/img/close.png
PythonOpencvJisuanjiShijueChuyi/img/fullscreen.png
PythonOpencvJisuanjiShijueChuyi/img/loader.gif
PythonOpencvJisuanjiShijueChuyi/img/menu-icon.png
PythonOpencvJisuanjiShijueChuyi/img/save.png
PythonOpencvJisuanjiShijueChuyi/img/saved.png
PythonOpencvJisuanjiShijueChuyi/img/settings-s.png
PythonOpencvJisuanjiShijueChuyi/img/settings.png
PythonOpencvJisuanjiShijueChuyi/img/star.png
PythonOpencvJisuanjiShijueChuyi/js/__init__.py
PythonOpencvJisuanjiShijueChuyi/js/epub.js
PythonOpencvJisuanjiShijueChuyi/js/epub.min.js
PythonOpencvJisuanjiShijueChuyi/js/epub.min.map
PythonOpencvJisuanjiShijueChuyi/js/hooks.min.js
PythonOpencvJisuanjiShijueChuyi/js/hooks.min.map
PythonOpencvJisuanjiShijueChuyi/js/reader.js
PythonOpencvJisuanjiShijueChuyi/js/reader.js.map
PythonOpencvJisuanjiShijueChuyi/js/reader.min.js
PythonOpencvJisuanjiShijueChuyi/js/reader.min.map
PythonOpencvJisuanjiShijueChuyi/js/hooks/__init__.py
python_opencv_jisuanji_shijue_chuyi-2024.3.6.0.dist-info/METADATA
python_opencv_jisuanji_shijue_chuyi-2024.3.6.0.dist-info/WHEEL
python_opencv_jisuanji_shijue_chuyi-2024.3.6.0.dist-info/entry_points.txt
python_opencv_jisuanji_shijue_chuyi-2024.3.6.0.dist-info/top_level.txt
python_opencv_jisuanji_shijue_chuyi-2024.3.6.0.dist-info/RECORD
